__init__.py
whoisapi/__init__.py
whoisapi/client.py
whoisapi/exceptions/__init__.py
whoisapi/exceptions/error.py
whoisapi/models/__init__.py
whoisapi/models/base.py
whoisapi/models/request.py
whoisapi/models/response.py
whoisapi/net/__init__.py
whoisapi/net/http.py
whois_api-1.2.0.dist-info/AUTHORS.rst
whois_api-1.2.0.dist-info/LICENSE
whois_api-1.2.0.dist-info/METADATA
whois_api-1.2.0.dist-info/WHEEL
whois_api-1.2.0.dist-info/top_level.txt
whois_api-1.2.0.dist-info/RECORD
