Metadata-Version: 2.1
Name: whois-api
Version: 1.2.0
Summary: Python client library for Whois API.
Home-page: https://github.com/whois-api-llc/whois-api-py
Author: WHOIS API, Inc
Author-email: support@whoisxmlapi.com
License: MIT
Keywords: whois,api,whoisxmlapi
Classifier: Development Status :: 5 - Production/Stable
Classifier: Intended Audience :: Developers
Classifier: License :: OSI Approved :: MIT License
Classifier: Operating System :: Unix
Classifier: Operating System :: POSIX
Classifier: Operating System :: Microsoft :: Windows
Classifier: Programming Language :: Python
Classifier: Programming Language :: Python :: 3
Classifier: Programming Language :: Python :: 3.7
Classifier: Programming Language :: Python :: 3.8
Classifier: Programming Language :: Python :: 3.9
Classifier: Programming Language :: Python :: 3.10
Classifier: Programming Language :: Python :: 3.11
Classifier: Topic :: Utilities
Requires-Python: ~=3.7
License-File: LICENSE
License-File: AUTHORS.rst
Requires-Dist: requests
Provides-Extra: dev
Requires-Dist: tox ; extra == 'dev'
